ermine/__init__.py
ermine/models/ErmineHMM.py
ermine/models/JumpDistanceMixtureModel.py
ermine/models/JumpDistanceModel.py
ermine/models/__init__.py
ermine/postprocessing/__init__.py
ermine/postprocessing/error_correction.py
ermine/postprocessing/likelihood_ratio_test.py
ermine/preprocessing/__init__.py
ermine/preprocessing/create_observation_sequence.py
ermine/preprocessing/init_transition_matrix.py
ermine/preprocessing/preprocess_swift_data.py
pyErmine-0.1.2.dist-info/LICENSE
pyErmine-0.1.2.dist-info/METADATA
pyErmine-0.1.2.dist-info/WHEEL
pyErmine-0.1.2.dist-info/top_level.txt
pyErmine-0.1.2.dist-info/RECORD
