Metadata-Version: 2.1
Name: pyErmine
Version: 0.1.2
Summary: Estimate Reaction-rates by Markov-based Investigation of Nanoscopy Experiments (ermine) using Python.
Home-page: https://github.com/SMLMS/pyErmine
Author: Sebastian Malkusch
Author-email: malkusch@med.uni-frankfurt.de
License: GNU General Public License v3 (GPLv3)
Keywords: hidden markov model,unsupervised learning,single particle tracking,biophysics
Platform: UNKNOWN
Classifier: Intended Audience :: Science/Research
Classifier: Programming Language :: Python :: 3
Classifier: Operating System :: MacOS :: MacOS X
Classifier: Operating System :: Microsoft :: Windows
Classifier: Operating System :: POSIX :: Linux
Requires-Python: >=3.5
Requires-Dist: hmmlearn (>=0.2.4)
Requires-Dist: numpy (>=1.19.2)
Requires-Dist: pandas (>=1.1.5)
Requires-Dist: scikit-learn (>=0.23.2)
